automationserver
cli
fieldagent
